examples/__init__.py
examples/sklearn-boston.py
examples/sklearn-digits.py
examples/sklearn-digits_params_tuning.py
examples/sklearn-digits_thresholding.py
examples/sklearn_boston.py
examples/sklearn_breastcancer_multiple_metrics.py
examples/sklearn_digits.py
examples/sklearn_digits_params_tuning.py
examples/sklearn_digits_thresholding.py
examples/kaggle_House_Prices_Advanced_Regression/FeatureEngineeringDataCleaner.py
examples/kaggle_House_Prices_Advanced_Regression/__init__.py
examples/kaggle_House_Prices_Advanced_Regression/kaggle_House_Prices_Advanced_Regression.py
sklearn_helper/__init__.py
sklearn_helper/data/DataCleaner.py
sklearn_helper/data/DummyCleaner.py
sklearn_helper/data/__init__.py
sklearn_helper/data/data_cleaner.py
sklearn_helper/data/dummy_cleaner.py
sklearn_helper/model/__init__.py
sklearn_helper/model/evaluator.py
sklearn_helper/model_finder/BestFitFinder.py
sklearn_helper/model_finder/__init__.py
sklearn_helper/model_procesors/ModelEvaluator.py
sklearn_helper/model_procesors/ModelOptimizer.py
sklearn_helper/model_procesors/__init__.py
sklearn_helper/model_procesors/model_evaluator.py
sklearn_helper/model_procesors/model_optimizer.py
sklearn_helper/output_processor/StandardOutputPrinter.py
sklearn_helper/output_processor/__init__.py
sklearn_helper/output_processor/standard_output_printer.py
sklearn_helper/tests/__init__.py
sklearn_helper/tests/model_finder/__init__.py
sklearn_helper/tests/model_finder/test_advance_best_fit_finder.py
sklearn_helper/tests/model_finder/test_basic_best_fit_finder.py
sklearn_helper/tests/model_finder/test_different_inputs_best_fit_finder.py
sklearn_helper/tests/util/__init__.py
sklearn_helper/tests/util/model_input_builder.py
sklearn_helper/tests/util/test_util.py
scikit_learn_helper-0.0.10.dist-info/METADATA
scikit_learn_helper-0.0.10.dist-info/WHEEL
scikit_learn_helper-0.0.10.dist-info/top_level.txt
scikit_learn_helper-0.0.10.dist-info/RECORD
