Metadata-Version: 1.1
Name: scikit_learn_helper
Version: 0.0.10
Summary: Helper code to make easier working with sklearn. https://github.com/aras7/scikit-learn-helper
Home-page: UNKNOWN
Author: Andres Arrieche
Author-email: andres.arrieche.7@gmail.com
License: Apache
Download-URL: https://pypi.org/project/scikit-learn-helper/#files
Platform: UNKNOWN
Classifier: Programming Language :: Python
Classifier: License :: OSI Approved :: Apache Software License
